raum_management/__init__.py
raum_management/main.py
raum_management-0.1.1.dist-info/METADATA
raum_management-0.1.1.dist-info/WHEEL
raum_management-0.1.1.dist-info/entry_points.txt
raum_management-0.1.1.dist-info/top_level.txt
raum_management-0.1.1.dist-info/RECORD
